{"api_bridge-api.md":"BlikM7zt","api_capability.md":"DLTud3g0","api_events.md":"RJJNJP_0","api_i18n.md":"BELecPLz","api_index.md":"BMOY5qHE","api_module-context.md":"ByQhBcxm","api_module-lifecycle.md":"14Np1m1H","appendix_changelog.md":"DXMibCUC","architecture_bridges.md":"CeiR0XYf","architecture_config-autofix.md":"JPbRESJp","architecture_cross-server.md":"oe7WdqO2","architecture_index.md":"FmXez0PZ","architecture_modular.md":"CbL24Ku2","architecture_packet-flow.md":"CMc3JGzz","architecture_protected-resources.md":"DeGhll8y","architecture_security.md":"Dg09Rb1q","architecture_system-architecture.md":"DMLfuYsC","guide_commands.md":"Dj_PWbwA","guide_config-management.md":"dYOQbE2f","guide_cross-server-setup.md":"CN1B9bLg","guide_currencies.md":"CNRrigBo","guide_first-run.md":"C-fvmr0Y","guide_index.md":"BcSFB8Dm","guide_installation.md":"DkrURhSN","guide_module-passwords.md":"Da8Hv0mI","guide_multi-ui.md":"B9fKex00","guide_placeholders.md":"D-VVfQzu","guide_proxy-usage.md":"uqpD8Bvn","index.md":"DXUKVSeG","modules_announcer.md":"CujkmITE","modules_chat.md":"CtUguQRU","modules_combateffect.md":"2eOohkOR","modules_conversation.md":"C7Okr1Fu","modules_entitytracker.md":"CJwkDRy0","modules_essentials.md":"Jpfl6WOW","modules_eventpacket.md":"CpRc-jRD","modules_index.md":"B6dxNeXG","modules_loginview.md":"C5QbCY8n","modules_mail.md":"CsSVdTsH","modules_map.md":"BcGzUt6y","modules_market.md":"D-7OmnV6","modules_onlinerewards.md":"Ddlyr8IG","modules_pickup.md":"DxjTtkTa","modules_prop.md":"MOpMDW-D","modules_qqbot.md":"VuXTjHDT","modules_questgps.md":"B7_OeJ2J","modules_regions.md":"DRxZ8FnJ","modules_rgb.md":"BBKVU3xy","modules_tab.md":"BL9tK5NI","modules_title.md":"3Rgv7678","modules_warehouse.md":"B1cwKMis"}
